h_vault_extractor_xethhung12/__init__.py
h_vault_extractor_xethhung12/__main__.py
h_vault_extractor_xethhung12/_module_h_vault_reader.py
h_vault_extractor_xethhung12/_cmd/run.py
h_vault_extractor_xethhung12-0.0.8.dist-info/METADATA
h_vault_extractor_xethhung12-0.0.8.dist-info/WHEEL
h_vault_extractor_xethhung12-0.0.8.dist-info/entry_points.txt
h_vault_extractor_xethhung12-0.0.8.dist-info/licenses/LICENSE
h_vault_extractor_xethhung12-0.0.8.dist-info/RECORD
