Metadata-Version: 2.4
Name: h_vault_extractor_xethhung12
Version: 0.0.8
Summary: A small package targeting to help on python project load hashicorp vault secret
Project-URL: Homepage, https://github.com/pypa/sampleproject
Project-URL: Issues, https://github.com/pypa/sampleproject/issues
Author-email: Xeth Hung <admin@xethh.me>
License-Expression: GPL-3.0-only
License-File: LICENSE
Classifier: Operating System :: OS Independent
Classifier: Programming Language :: Python :: 3
Requires-Python: >=3.11
Requires-Dist: hvac
Requires-Dist: j-vault-http-client-xethhung12>=0.1.1
